sukiyouall/__init__.py
sukiyou_all-1.0.5.1.dist-info/LICENSE
sukiyou_all-1.0.5.1.dist-info/METADATA
sukiyou_all-1.0.5.1.dist-info/WHEEL
sukiyou_all-1.0.5.1.dist-info/top_level.txt
sukiyou_all-1.0.5.1.dist-info/RECORD
