Metadata-Version: 2.1
Name: sukiyou-all
Version: 1.0.5.1
Summary: sukiyou-all
Author: sukiyou
Author-email: s844562300@163.com
Classifier: Programming Language :: Python :: 3
Classifier: License :: OSI Approved :: MIT License
Classifier: Operating System :: OS Independent
Requires-Python: >=3.6
License-File: LICENSE
Requires-Dist: flask
Requires-Dist: flask-cors
Requires-Dist: pymysql
Requires-Dist: requests
Requires-Dist: sqlalchemy
Requires-Dist: sukiyou-sql
Requires-Dist: pyjwt (==2.5.0)
